ktpanda/cli.py
ktpanda/dateutils.py
ktpanda/dictutils.py
ktpanda/dsl.py
ktpanda/fileutils.py
ktpanda/git_filter.py
ktpanda/git_helper.py
ktpanda/hotload.py
ktpanda/logutils.py
ktpanda/object_pool.py
ktpanda/roundtrip_encoding.py
ktpanda/sqlite_helper.py
ktpanda/textcolor.py
ktpanda/textutil.py
ktpanda/threadpool.py
ktpanda/ttyutil.py
ktpanda/versioning.py
ktpanda/vt100.py
ktpanda/xmledit.py
ktpanda_modules-1.0.48.dist-info/LICENSE
ktpanda_modules-1.0.48.dist-info/METADATA
ktpanda_modules-1.0.48.dist-info/WHEEL
ktpanda_modules-1.0.48.dist-info/top_level.txt
ktpanda_modules-1.0.48.dist-info/RECORD
