Metadata-Version: 2.2
Name: ktpanda-modules
Version: 1.0.48
Summary: A collection of miscellaneous utility modules
Home-page: https://ktpanda.org/software/ktpanda-modules
Author: Katie Rust
Author-email: katie@ktpanda.org
License: MIT License
Classifier: Programming Language :: Python :: 3
Classifier: License :: OSI Approved :: MIT License
Classifier: Operating System :: OS Independent
Requires-Python: >=3.8
License-File: LICENSE
